worai/__init__.py
worai/cli.py
worai/config.py
worai/errors.py
worai/logging.py
worai/commands/__init__.py
worai/commands/canonicalize_duplicate_pages.py
worai/commands/dedupe.py
worai/commands/delete_entities_from_csv.py
worai/commands/find_faq_page_wrong_type.py
worai/commands/find_missing_names.py
worai/commands/find_url_by_type.py
worai/commands/google_search_console.py
worai/commands/link_groups.py
worai/commands/list_entities_outside_dataset.py
worai/commands/patch.py
worai/commands/seocheck.py
worai/commands/structured_data.py
worai/commands/upload_entities_from_turtle.py
worai/commands/validate.py
worai/core/__init__.py
worai/core/canonicalize_duplicate_pages.py
worai/core/dedupe.py
worai/core/delete_entities_from_csv.py
worai/core/find_faq_page_wrong_type.py
worai/core/find_missing_names.py
worai/core/find_url_by_type.py
worai/core/gsc.py
worai/core/html_to_xhtml.py
worai/core/link_groups.py
worai/core/patch.py
worai/core/prune_entities_outside_dataset.py
worai/core/structured_data.py
worai/core/upload_entities_from_turtle.py
worai/core/validate_shacl.py
worai/core/wordlift.py
worai/seocheck/__init__.py
worai/seocheck/browser.py
worai/seocheck/cli.py
worai/seocheck/sitemap.py
worai/seocheck/checks/__init__.py
worai/seocheck/checks/canonical.py
worai/seocheck/checks/llms_txt.py
worai/seocheck/checks/page_meta.py
worai/seocheck/checks/resource_404.py
worai/seocheck/checks/response_time.py
worai/seocheck/checks/robots_txt.py
worai/seocheck/checks/status.py
worai/seocheck/checks/ttfb.py
worai/seocheck/checks/types.py
worai/seocheck/checks/wordlift_bootstrap.py
worai/seoreport/__init__.py
worai/seoreport/cli.py
worai/seoreport/core.py
worai/validate/__init__.py
worai/validate/shacls/__init__.py
worai/validate/shacls/google-article.ttl
worai/validate/shacls/google-book.ttl
worai/validate/shacls/google-breadcrumb.ttl
worai/validate/shacls/google-carousel.ttl
worai/validate/shacls/google-carousels-beta.ttl
worai/validate/shacls/google-course.ttl
worai-1.6.0.dist-info/METADATA
worai-1.6.0.dist-info/WHEEL
worai-1.6.0.dist-info/entry_points.txt
worai-1.6.0.dist-info/top_level.txt
worai-1.6.0.dist-info/RECORD
