Metadata-Version: 2.4
Name: worai
Version: 1.6.0
Summary: Add your description here
Requires-Python: >=3.11
Requires-Dist: advertools>=0.16.0
Requires-Dist: google-auth>=2.35.0
Requires-Dist: google-auth-oauthlib>=1.2.1
Requires-Dist: jinja2>=3.1.0
Requires-Dist: lxml>=5.3.0
Requires-Dist: morph-kgc>=2.7.0
Requires-Dist: playwright>=1.48.0
Requires-Dist: pyshacl>=0.26.0
Requires-Dist: rdflib>=7.5.0
Requires-Dist: requests>=2.32.5
Requires-Dist: tqdm>=4.67.1
Requires-Dist: typer>=0.12.5
Requires-Dist: wordlift-sdk>=2.9.1
Provides-Extra: dev
Requires-Dist: pytest>=8.3.4; extra == "dev"
